AUTHORS.rst
CONTRIBUTING.rst
HISTORY.rst
LICENSE
MANIFEST.in
README.rst
setup.cfg
setup.py
django_random_filestorage.egg-info/PKG-INFO
django_random_filestorage.egg-info/SOURCES.txt
django_random_filestorage.egg-info/dependency_links.txt
django_random_filestorage.egg-info/not-zip-safe
django_random_filestorage.egg-info/top_level.txt
randomfilestorage/__init__.py
randomfilestorage/storage.py