Metadata-Version: 1.1
Name: django-random-filestorage
Version: 0.1.0
Summary: Django storage class that assigns random filenames to all stored files.
Home-page: https://github.com/erikr/django-random-filestorage
Author: Erik Romijn
Author-email: eromijn@solidlinks.nl
License: BSD
Keywords: django-random-filestorage
Platform: UNKNOWN
Classifier: Development Status :: 4 - Beta
Classifier: Framework :: Django
Classifier: Intended Audience :: Developers
Classifier: License :: OSI Approved :: BSD License
Classifier: Natural Language :: English
Classifier: Programming Language :: Python :: 2
Classifier: Programming Language :: Python :: 2.6
Classifier: Programming Language :: Python :: 2.7
Classifier: Programming Language :: Python :: 3
Classifier: Programming Language :: Python :: 3.3
